mtsespy/__init__.py
mtsespy/_mtsespy.cpython-314t-aarch64-linux-gnu.so
mtsespy/context_managers.py
mtsespy/mtsespy.cpp
mtsespy-1.1.0.dist-info/METADATA
mtsespy-1.1.0.dist-info/WHEEL
mtsespy-1.1.0.dist-info/RECORD
mtsespy-1.1.0.dist-info/licenses/LICENSE
