Metadata-Version: 2.2
Name: mtsespy
Version: 1.1.0
Summary: Python bindings for ODDSound MTS-ESP
Author: Naren Ratan
License: Copyright (C) 2023 by Naren Ratan
Project-URL: Homepage, https://github.com/narenratan/mtsespy
Project-URL: Issues, https://github.com/narenratan/mtsespy/issues
Requires-Python: >=3.8
